iv/__init__.py
iv/schemas.py
iv/cirtorch/__init__.py
iv/cirtorch/datasets/__init__.py
iv/cirtorch/datasets/genericdataset.py
iv/cirtorch/layers/__init__.py
iv/cirtorch/layers/functional.py
iv/cirtorch/layers/normalization.py
iv/cirtorch/layers/pooling.py
iv/cirtorch/networks/__init__.py
iv/cirtorch/networks/imageretrievalnet.py
image2vector-1.1.0.dist-info/METADATA
image2vector-1.1.0.dist-info/WHEEL
image2vector-1.1.0.dist-info/top_level.txt
image2vector-1.1.0.dist-info/RECORD
